{
  "project_info": {
    "project_number": "986364414232",
    "project_id": "flutter-todo-app-188bb",
    "storage_bucket": "flutter-todo-app-188bb.appspot.com"
  },
  "client": [
    {
      "client_info": {
        "mobilesdk_app_id": "1:986364414232:android:91c122fa5cd1817882766d",
        "android_client_info": {
          "package_name": "com.example.flutter_todo_app"
        }
      },
      "oauth_client": [
        {
          "client_id": "986364414232-60g2jm7don0uvpsv7s9busq2jbd9649s.apps.googleusercontent.com",
          "client_type": 3
        }
      ],
      "api_key": [
        {
          "current_key": "AIzaSyB1DOilewlNWPSeylaLkE2B_1Fdu1rAMeo"
        }
      ],
      "services": {
        "appinvite_service": {
          "other_platform_oauth_client": [
            {
              "client_id": "986364414232-60g2jm7don0uvpsv7s9busq2jbd9649s.apps.googleusercontent.com",
              "client_type": 3
            }
          ]
        }
      }
    }
  ],
  "configuration_version": "1"
}